nonebot/adapters/rocketchat/__init__.py
nonebot/adapters/rocketchat/adapter.py
nonebot/adapters/rocketchat/bot.py
nonebot/adapters/rocketchat/config.py
nonebot/adapters/rocketchat/event.py
nonebot/adapters/rocketchat/log.py
nonebot/adapters/rocketchat/message.py
nonebot/adapters/rocketchat/model.py
nonebot/adapters/rocketchat/realtime/__init__.py
nonebot/adapters/rocketchat/realtime/constants.py
nonebot/adapters/rocketchat/realtime/core.py
nonebot/adapters/rocketchat/realtime/dispatcher.py
nonebot/adapters/rocketchat/realtime/methods.py
nonebot_adapter_rocketchat-0.1.0.dist-info/WHEEL
nonebot_adapter_rocketchat-0.1.0.dist-info/METADATA
nonebot_adapter_rocketchat-0.1.0.dist-info/licenses/LICENSE
nonebot_adapter_rocketchat-0.1.0.dist-info/RECORD
