Metadata-Version: 2.1
Name: nonebot-adapter-rocketchat
Version: 0.1.0
Summary: RocketChat adapter for nonebot2
Keywords: bot,nonebot,Rocket.Chat
Author-email: IllTamer <mail@illtamer.com>
Requires-Python: >=3.8, <4.0
Classifier: Development Status :: 4 - Beta
Classifier: Framework :: Robot Framework
Classifier: Framework :: Robot Framework :: Library
Classifier: License :: OSI Approved :: GNU Affero General Public License v3 or later (AGPLv3+)
Classifier: Operating System :: OS Independent
Classifier: Programming Language :: Python :: 3
Requires-Dist: nonebot2<3.0.0,>=2.1.3
Requires-Dist: rocket-python<2.0.0,>=1.3.1
Project-URL: documentation, https://github.com/IUnlimit/nonebot-adapter-rocketchat/blob/main/README.md
Project-URL: homepage, https://github.com/IUnlimit
Project-URL: repository, https://github.com/IUnlimit/nonebot-adapter-rocketchat
